Workbook

Sheet Read Me
B2: Dangote Cement Plc | Excel Equity Research Model
B4: Purpose | C4: Model convention | D4: Blue font | E4: Green font | F4: Black font | G4: Yellow fill | H4: Units
B5: Portfolio-ready equity research model | C5: Inputs are editable | D5: Hardcoded inputs | E5: Cross-sheet formulas | F5: Calculations | G5: Update/attention | H5: ₦ billion unless stated
B7: How to Use
B8: 1. Review historical data and source notes. | C8: Important: The workbook is an educational portfolio model. 2025 revenue, EBITDA, capacity and reference share price are based on the cited official investor-relations page. Other operating, balance-sheet, forecast and peer inputs are illustrative placeholders so the model remains complete and functional. They are clearly labelled and should not be represented as audited facts.
B9: 2. Update blue-font assumptions in Forecast Assumptions.
B10: 3. Review forecast statements and DCF outputs.
B11: 4. Update peer market data in Comparable Companies.
B12: 5. Read the dashboard and write a concise investment thesis.
B13: 6. Replace illustrative inputs with audited/market data before publication.
B15: Core Outputs
B16: Output | C16: Location
B17: Historical ratio analysis | C17: Historical Financials
B18: Five-year integrated forecast | C18: Financial Forecast
B19: DCF and implied value per share | C19: DCF Valuation
B20: Peer valuation cross-check | C20: Comparable Companies

Sheet Company Overview
B2: Company Overview & Research Framework
B4: Company Snapshot
B5: Item | C5: Research note
B6: Company | C6: Dangote Cement Plc
B7: Ticker | C7: DANGCEM
B8: Listing | C8: Nigerian Exchange Limited
B9: Business | C9: Manufacture, sale and distribution of cement and related products across African markets
B10: Portfolio question | C10: Is the current market price supported by fundamentals and intrinsic value?
B11: Base currency / units | C11: Nigerian naira; financial statements in ₦ billion
B13: Research Drives, Catalysts & Risks
B14: Category | C14: Factor | D14: Why it matters | E14: Indicator to monitor | F14: Model linkage | G14: Analyst view
B15: Revenue driver | C15: Volume growth | D15: Drives plant utilisation and revenue | E15: Sales volume / capacity utilisation | F15: Revenue growth | G15: Positive if demand outpaces cost inflation
B16: Revenue driver | C16: Pricing | D16: Offsets inflation and FX pressure | E16: Average selling price | F16: Revenue growth | G16: Requires demand resilience
B17: Cost driver | C17: Energy and fuel | D17: Material EBITDA-margin sensitivity | E17: Energy cost / tonne | F17: EBITDA margin | G17: Key downside risk
B18: Macro | C18: FX and inflation | D18: Affects imported inputs, pricing and discount rate | E18: NGN rate / CPI / yields | F18: WACC and margins | G18: Raises valuation uncertainty
B19: Catalyst | C19: Capacity utilisation | D19: Improves operating leverage | E19: Production volume | F19: Margins and capex | G19: Upside if fixed-cost absorption improves
B20: Risk | C20: Debt and interest cost | D20: Can reduce equity value and earnings | E20: Net debt / interest coverage | F20: DCF bridge | G20: Monitor refinancing risk
B21: ESG | C21: Emissions intensity | D21: May increase compliance/capex needs | E21: CO2 per tonne | F21: Capex / terminal value | G21: Long-term strategic risk

Sheet Historical Financials
B2: Historical Financial Analysis
B4: ₦ billion unless stated | C4: 2023A | D4: 2024A | E4: 2025A | F4: Source / status
B5: Revenue | C5: 2400 | D5: 3500 | E5: 4306.704 | F5: 2025 official; 2023-24 illustrative
B6: COGS | C6: -1050 | D6: -1550 | E6: -1850 | F6: Illustrative placeholder
B7: Gross profit | C7: =C5+C6 -> 1350 | D7: =D5+D6 -> 1950 | E7: =E5+E6 -> 2456.704 | F7: Illustrative placeholder
B8: EBITDA | C8: 950 | D8: 1380 | E8: 1981.349 | F8: 2025 official; 2023-24 illustrative
B9: EBIT | C9: 780 | D9: 1130 | E9: 1700 | F9: Illustrative placeholder
B10: Net finance cost | C10: -110 | D10: -160 | E10: -210 | F10: Illustrative placeholder
B11: Profit before tax | C11: 670 | D11: 970 | E11: 1490 | F11: Illustrative placeholder
B12: Tax | C12: -235 | D12: -340 | E12: -520 | F12: Illustrative placeholder
B13: Net income | C13: 435 | D13: 630 | E13: 970 | F13: Illustrative placeholder
B14: Total assets | C14: 4800 | D14: 6100 | E14: 7500 | F14: Illustrative placeholder
B15: Total equity | C15: 2500 | D15: 3050 | E15: 3800 | F15: Illustrative placeholder
B16: Gross debt | C16: 900 | D16: 1150 | E16: 1400 | F16: Illustrative placeholder
B17: Cash | C17: =C15-C16 -> 1600 | D17: =D15-D16 -> 1900 | E17: =E15-E16 -> 2400 | F17: Illustrative placeholder
B18: Net debt | F18: Illustrative placeholder
B19: Operating cash flow | C19: 700 | D19: 1030 | E19: 1450 | F19: Illustrative placeholder
B20: Capital expenditure | C20: -380 | D20: -480 | E20: -620 | F20: Illustrative placeholder
B21: Free cash flow | C21: =C19+C20 -> 320 | D21: =D19+D20 -> 550 | E21: =E19+E20 -> 830 | F21: Illustrative placeholder
B22: Shares outstanding (bn) | C22: 17.04 | D22: 17.04 | E22: 17.04 | F22: Illustrative placeholder
B24: Key Financial Ratios
B25: Ratio | C25: 2023A | D25: 2024A | E25: 2025A | F25: Formula
B26: Revenue growth | C26: =NA() -> #N/A | D26: =D5/C5-1 -> 0.45833333 | E26: =E5/D5-1 -> 0.23048686 | F26: Current revenue / prior revenue - 1
B27: Gross margin | C27: =C7/C5 -> 0.5625 | D27: =D7/D5 -> 0.55714286 | E27: =E7/E5 -> 0.57043716 | F27: Gross profit / revenue
B28: EBITDA margin | C28: =C8/C5 -> 0.39583333 | D28: =D8/D5 -> 0.39428571 | E28: =E8/E5 -> 0.46006157 | F28: EBITDA / revenue
B29: Net profit margin | C29: =C13/C5 -> 0.18125 | D29: =D13/D5 -> 0.18 | E29: =E13/E5 -> 0.22523025 | F29: Net income / revenue
B30: Return on assets | C30: =C13/C14 -> 0.090625 | D30: =D13/D14 -> 0.10327869 | E30: =E13/E14 -> 0.12933333 | F30: Net income / total assets
B31: Return on equity | C31: =C13/C15 -> 0.174 | D31: =D13/D15 -> 0.20655738 | E31: =E13/E15 -> 0.25526316 | F31: Net income / equity
B32: Debt / equity | C32: =C16/C15 -> 0.36 | D32: =D16/D15 -> 0.37704918 | E32: =E16/E15 -> 0.36842105 | F32: Gross debt / equity
B33: Interest coverage | C33: =C9/ABS(C10) -> 7.0909091 | D33: =D9/ABS(D10) -> 7.0625 | E33: =E9/ABS(E10) -> 8.0952381 | F33: EBIT / absolute finance cost

Sheet Forecast Assumptions
B2: Forecast Assumptions & Scenarios
B4: Assumption | C4: 2026E | D4: 2027E | E4: 2028E | F4: 2029E | G4: 2030E | H4: Rationale
B5: Revenue growth | C5: 0.15 | D5: 0.13 | E5: 0.11 | F5: 0.1 | G5: 0.09 | H5: Volume, pricing and market growth
B6: EBITDA margin | C6: 0.44 | D6: 0.43 | E6: 0.42 | F6: 0.42 | G6: 0.41 | H6: Normalisation from strong 2025 base
B7: D&A as % revenue | C7: 0.055 | D7: 0.055 | E7: 0.054 | F7: 0.053 | G7: 0.052 | H7: Asset-intensive operations
B8: Tax rate | C8: 0.34 | D8: 0.34 | E8: 0.34 | F8: 0.34 | G8: 0.34 | H8: Illustrative effective rate
B9: Capex as % revenue | C9: 0.13 | D9: 0.12 | E9: 0.11 | F9: 0.1 | G9: 0.09 | H9: Capacity and maintenance investment
B10: NWC as % revenue | C10: 0.07 | D10: 0.07 | E10: 0.07 | F10: 0.07 | G10: 0.07 | H10: Operating working-capital requirement
B12: DCF & Market Assumptions
B13: Risk-free rate | C13: 0.16 | D13: Illustrative long-term NGN government yield
B14: Equity risk premium | C14: 0.06 | D14: Illustrative market risk premium
B15: Beta | C15: 0.9 | D15: Illustrative levered beta
B16: Pre-tax cost of debt | C16: 0.19 | D16: Illustrative borrowing cost
B17: Debt weight | C17: 0.2 | D17: Capital structure assumption
B18: Equity weight | C18: 0.8 | D18: Capital structure assumption
B19: Terminal growth rate | C19: 0.06 | D19: Long-term nominal growth assumption
B20: Reference share price | C20: 1066.7 | D20: Official investor-relations page, 16 Oct 2026
B21: Shares outstanding (bn) | C21: 17.04 | D21: Illustrative; update from latest annual report
B22: Gross debt (₦bn) | C22: 1400 | D22: Illustrative; linked to historical model
B23: Cash (₦bn) | C23: 450 | D23: Illustrative; linked to historical model

Sheet Financial Forecast
B2: Five-Year Financial Forecast
B4: ₦ billion unless stated | C4: 2026E | D4: 2027E | E4: 2028E | F4: 2029E | G4: 2030E
B5: Revenue | C5: ='Historical Financials'!E5*(1+'Forecast Assumptions'!C5) -> 4952.7096 | D5: =C5*(1+'Forecast Assumptions'!D5) -> 5596.5618 | E5: =D5*(1+'Forecast Assumptions'!E5) -> 6212.1837 | F5: =E5*(1+'Forecast Assumptions'!F5) -> 6833.402 | G5: =F5*(1+'Forecast Assumptions'!G5) -> 7448.4082
B6: Growth | C6: ='Forecast Assumptions'!C5 -> 0.15 | D6: ='Forecast Assumptions'!D5 -> 0.13 | E6: ='Forecast Assumptions'!E5 -> 0.11 | F6: ='Forecast Assumptions'!F5 -> 0.1 | G6: ='Forecast Assumptions'!G5 -> 0.09
B7: EBITDA | C7: =C5*'Forecast Assumptions'!C6 -> 2179.1922 | D7: =D5*'Forecast Assumptions'!D6 -> 2406.5216 | E7: =E5*'Forecast Assumptions'!E6 -> 2609.1171 | F7: =F5*'Forecast Assumptions'!F6 -> 2870.0288 | G7: =G5*'Forecast Assumptions'!G6 -> 3053.8474
B8: EBITDA margin | C8: ='Forecast Assumptions'!C6 -> 0.44 | D8: ='Forecast Assumptions'!D6 -> 0.43 | E8: ='Forecast Assumptions'!E6 -> 0.42 | F8: ='Forecast Assumptions'!F6 -> 0.42 | G8: ='Forecast Assumptions'!G6 -> 0.41
B9: D&A | C9: =-C5*'Forecast Assumptions'!C7 -> -272.39903 | D9: =-D5*'Forecast Assumptions'!D7 -> -307.8109 | E9: =-E5*'Forecast Assumptions'!E7 -> -335.45792 | F9: =-F5*'Forecast Assumptions'!F7 -> -362.17031 | G9: =-G5*'Forecast Assumptions'!G7 -> -387.31723
B10: EBIT | C10: =C7+C9 -> 1906.7932 | D10: =D7+D9 -> 2098.7107 | E10: =E7+E9 -> 2273.6592 | F10: =F7+F9 -> 2507.8585 | G10: =G7+G9 -> 2666.5301
B11: Tax on EBIT | C11: =-C10*'Forecast Assumptions'!C8 -> -648.30969 | D11: =-D10*'Forecast Assumptions'!D8 -> -713.56164 | E11: =-E10*'Forecast Assumptions'!E8 -> -773.04413 | F11: =-F10*'Forecast Assumptions'!F8 -> -852.6719 | G11: =-G10*'Forecast Assumptions'!G8 -> -906.62025
B12: NOPAT | C12: =C10+C11 -> 1258.4835 | D12: =D10+D11 -> 1385.1491 | E12: =E10+E11 -> 1500.6151 | F12: =F10+F11 -> 1655.1866 | G12: =G10+G11 -> 1759.9099
B13: NWC | C13: =C5*'Forecast Assumptions'!C10 -> 346.68967 | D13: =D5*'Forecast Assumptions'!D10 -> 391.75933 | E13: =E5*'Forecast Assumptions'!E10 -> 434.85286 | F13: =F5*'Forecast Assumptions'!F10 -> 478.33814 | G13: =G5*'Forecast Assumptions'!G10 -> 521.38857
B14: Change in NWC | C14: =-(C13-'Historical Financials'!E5*'Forecast Assumptions'!C10) -> -45.220392 | D14: =-(D13-C13) -> -45.069657 | E14: =-(E13-D13) -> -43.093526 | F14: =-(F13-E13) -> -43.485286 | G14: =-(G13-F13) -> -43.050433
B15: Capital expenditure | C15: =-C5*'Forecast Assumptions'!C9 -> -643.85225 | D15: =-D5*'Forecast Assumptions'!D9 -> -671.58742 | E15: =-E5*'Forecast Assumptions'!E9 -> -683.3402 | F15: =-F5*'Forecast Assumptions'!F9 -> -683.3402 | G15: =-G5*'Forecast Assumptions'!G9 -> -670.35674
B16: Unlevered free cash flow | C16: =C12-C9+C14+C15 -> 841.8099 | D16: =D12-D9+D14+D15 -> 976.30288 | E16: =E12-E9+E14+E15 -> 1109.6393 | F16: =F12-F9+F14+F15 -> 1290.5315 | G16: =G12-G9+G14+G15 -> 1433.8199

Sheet DCF Valuation
B2: Discounted Cash flow Valuation
B4: WACC Calculation
B5: Item | C5: Value | D5: Formula / note
B6: Cost of equity | C6: ='Forecast Assumptions'!C13+'Forecast Assumptions'!C15*'Forecast Assumptions'!C14 -> 0.214 | D6: Rf + beta × ERP
B7: After-tax cost of debt | C7: ='Forecast Assumptions'!C16*(1-'Forecast Assumptions'!C8) -> 0.1254 | D7: Pre-tax cost × (1-tax rate)
B8: WACC | C8: =C6*'Forecast Assumptions'!C18+C7*'Forecast Assumptions'!C17 -> 0.19628 | D8: Ke × E weight + Kd × D weight
B10: DCF Schedule
B11: Metric | C11: 2026E | D11: 2027E | E11: 2028E | F11: 2029E | G11: 2030E | H11: Terminal
B12: Unlevered FCF | C12: ='Financial Forecast'!C16 -> 841.8099 | D12: ='Financial Forecast'!D16 -> 976.30288 | E12: ='Financial Forecast'!E16 -> 1109.6393 | F12: ='Financial Forecast'!F16 -> 1290.5315 | G12: ='Financial Forecast'!G16 -> 1433.8199 | H12: =G12*(1+'Forecast Assumptions'!C19)/($C$8-'Forecast Assumptions'!C19) -> 11152.401
B13: Discount period | C13: 1 | D13: 2 | E13: 3 | F13: 4 | G13: 5
B14: Discount factor | C14: =1/(1+$C$8)^C13 -> 0.8359247 | D14: =1/(1+$C$8)^D13 -> 0.6987701 | E14: =1/(1+$C$8)^E13 -> 0.58411919 | F14: =1/(1+$C$8)^F13 -> 0.48827966 | G14: =1/(1+$C$8)^G13 -> 0.40816503 | H14: =G14 -> 0.40816503
B15: Present value | C15: =C12*C14 -> 703.68969 | D15: =D12*D14 -> 682.21126 | E15: =E12*E14 -> 648.16159 | F15: =F12*F14 -> 630.14026 | G15: =G12*G14 -> 585.23516 | H15: =H12*H14 -> 4552.0199
B17: Equity Value Bridge
B18: Enterprise value | C18: =SUM(C15:H15) -> 7801.4578
B19: Less: gross debt | C19: =-'Forecast Assumptions'!C22 -> -1400
B20: Add: cash | C20: ='Forecast Assumptions'!C23 -> 450
B21: Equity value | C21: =SUM(C18:C20) -> 6851.4578
B22: Shares outstanding (bn) | C22: ='Forecast Assumptions'!C21 -> 17.04
B23: Implied value per share | C23: =C21/C22 -> 402.08086
B24: Reference share price | C24: ='Forecast Assumptions'!C20 -> 1066.7
B25: Upside / (downside) | C25: =C23/C24-1 -> -0.62306098
B26: Recommendation | C26: =IF(C25>15%,"BUY",IF(C25<-15%,"SELL","HOLD")) -> SELL
B28: DCF Sensitivity: Implied Value Per Share (₦)
B29: WACC \ TGR | C29: 0.04 | D29: 0.05 | E29: 0.06 | F29: 0.07 | G29: 0.08
B30: 0.18 | C30: =(SUMPRODUCT($C$12:$G$12,1/(1+0.18)^$C$13:$G$13)+$G$12*(1+0.04)/(0.18-0.04)/(1+0.18)^5-'Forecast Assumptions'!C22+'Forecast Assumptions'!C23)/'Forecast Assumptions'!C21 -> 415.96565 | D30: =(SUMPRODUCT($C$12:$G$12,1/(1+0.18)^$C$13:$G$13)+$G$12*(1+0.05)/(0.18-0.05)/(1+0.18)^5-'Forecast Assumptions'!C22+'Forecast Assumptions'!C23)/'Forecast Assumptions'!C21 -> 439.8122 | E30: =(SUMPRODUCT($C$12:$G$12,1/(1+0.18)^$C$13:$G$13)+$G$12*(1+0.06)/(0.18-0.06)/(1+0.18)^5-'Forecast Assumptions'!C22+'Forecast Assumptions'!C23)/'Forecast Assumptions'!C21 -> 467.63318 | F30: =(SUMPRODUCT($C$12:$G$12,1/(1+0.18)^$C$13:$G$13)+$G$12*(1+0.07)/(0.18-0.07)/(1+0.18)^5-'Forecast Assumptions'!C22+'Forecast Assumptions'!C23)/'Forecast Assumptions'!C21 -> 500.51252 | G30: =(SUMPRODUCT($C$12:$G$12,1/(1+0.18)^$C$13:$G$13)+$G$12*(1+0.08)/(0.18-0.08)/(1+0.18)^5-'Forecast Assumptions'!C22+'Forecast Assumptions'!C23)/'Forecast Assumptions'!C21 -> 539.96772
B31: 0.19 | C31: =(SUMPRODUCT($C$12:$G$12,1/(1+0.19)^$C$13:$G$13)+$G$12*(1+0.04)/(0.19-0.04)/(1+0.19)^5-'Forecast Assumptions'!C22+'Forecast Assumptions'!C23)/'Forecast Assumptions'!C21 -> 382.36701 | D31: =(SUMPRODUCT($C$12:$G$12,1/(1+0.19)^$C$13:$G$13)+$G$12*(1+0.05)/(0.19-0.05)/(1+0.19)^5-'Forecast Assumptions'!C22+'Forecast Assumptions'!C23)/'Forecast Assumptions'!C21 -> 402.34804 | E31: =(SUMPRODUCT($C$12:$G$12,1/(1+0.19)^$C$13:$G$13)+$G$12*(1+0.06)/(0.19-0.06)/(1+0.19)^5-'Forecast Assumptions'!C22+'Forecast Assumptions'!C23)/'Forecast Assumptions'!C21 -> 425.40308 | F31: =(SUMPRODUCT($C$12:$G$12,1/(1+0.19)^$C$13:$G$13)+$G$12*(1+0.07)/(0.19-0.07)/(1+0.19)^5-'Forecast Assumptions'!C22+'Forecast Assumptions'!C23)/'Forecast Assumptions'!C21 -> 452.30062 | G31: =(SUMPRODUCT($C$12:$G$12,1/(1+0.19)^$C$13:$G$13)+$G$12*(1+0.08)/(0.19-0.08)/(1+0.19)^5-'Forecast Assumptions'!C22+'Forecast Assumptions'!C23)/'Forecast Assumptions'!C21 -> 484.08862
B32: 0.2 | C32: =(SUMPRODUCT($C$12:$G$12,1/(1+0.2)^$C$13:$G$13)+$G$12*(1+0.04)/(0.2-0.04)/(1+0.2)^5-'Forecast Assumptions'!C22+'Forecast Assumptions'!C23)/'Forecast Assumptions'!C21 -> 353.03181 | D32: =(SUMPRODUCT($C$12:$G$12,1/(1+0.2)^$C$13:$G$13)+$G$12*(1+0.05)/(0.2-0.05)/(1+0.2)^5-'Forecast Assumptions'!C22+'Forecast Assumptions'!C23)/'Forecast Assumptions'!C21 -> 369.93968 | E32: =(SUMPRODUCT($C$12:$G$12,1/(1+0.2)^$C$13:$G$13)+$G$12*(1+0.06)/(0.2-0.06)/(1+0.2)^5-'Forecast Assumptions'!C22+'Forecast Assumptions'!C23)/'Forecast Assumptions'!C21 -> 389.26295 | F32: =(SUMPRODUCT($C$12:$G$12,1/(1+0.2)^$C$13:$G$13)+$G$12*(1+0.07)/(0.2-0.07)/(1+0.2)^5-'Forecast Assumptions'!C22+'Forecast Assumptions'!C23)/'Forecast Assumptions'!C21 -> 411.55904 | G32: =(SUMPRODUCT($C$12:$G$12,1/(1+0.2)^$C$13:$G$13)+$G$12*(1+0.08)/(0.2-0.08)/(1+0.2)^5-'Forecast Assumptions'!C22+'Forecast Assumptions'!C23)/'Forecast Assumptions'!C21 -> 437.57114
B33: 0.21 | C33: =(SUMPRODUCT($C$12:$G$12,1/(1+0.21)^$C$13:$G$13)+$G$12*(1+0.04)/(0.21-0.04)/(1+0.21)^5-'Forecast Assumptions'!C22+'Forecast Assumptions'!C23)/'Forecast Assumptions'!C21 -> 327.20519 | D33: =(SUMPRODUCT($C$12:$G$12,1/(1+0.21)^$C$13:$G$13)+$G$12*(1+0.05)/(0.21-0.05)/(1+0.21)^5-'Forecast Assumptions'!C22+'Forecast Assumptions'!C23)/'Forecast Assumptions'!C21 -> 341.63679 | E33: =(SUMPRODUCT($C$12:$G$12,1/(1+0.21)^$C$13:$G$13)+$G$12*(1+0.06)/(0.21-0.06)/(1+0.21)^5-'Forecast Assumptions'!C22+'Forecast Assumptions'!C23)/'Forecast Assumptions'!C21 -> 357.99261 | F33: =(SUMPRODUCT($C$12:$G$12,1/(1+0.21)^$C$13:$G$13)+$G$12*(1+0.07)/(0.21-0.07)/(1+0.21)^5-'Forecast Assumptions'!C22+'Forecast Assumptions'!C23)/'Forecast Assumptions'!C21 -> 376.68498 | G33: =(SUMPRODUCT($C$12:$G$12,1/(1+0.21)^$C$13:$G$13)+$G$12*(1+0.08)/(0.21-0.08)/(1+0.21)^5-'Forecast Assumptions'!C22+'Forecast Assumptions'!C23)/'Forecast Assumptions'!C21 -> 398.25309
B34: 0.22 | C34: =(SUMPRODUCT($C$12:$G$12,1/(1+0.22)^$C$13:$G$13)+$G$12*(1+0.04)/(0.22-0.04)/(1+0.22)^5-'Forecast Assumptions'!C22+'Forecast Assumptions'!C23)/'Forecast Assumptions'!C21 -> 304.30015 | D34: =(SUMPRODUCT($C$12:$G$12,1/(1+0.22)^$C$13:$G$13)+$G$12*(1+0.05)/(0.22-0.05)/(1+0.22)^5-'Forecast Assumptions'!C22+'Forecast Assumptions'!C23)/'Forecast Assumptions'!C21 -> 316.71279 | E34: =(SUMPRODUCT($C$12:$G$12,1/(1+0.22)^$C$13:$G$13)+$G$12*(1+0.06)/(0.22-0.06)/(1+0.22)^5-'Forecast Assumptions'!C22+'Forecast Assumptions'!C23)/'Forecast Assumptions'!C21 -> 330.67702 | F34: =(SUMPRODUCT($C$12:$G$12,1/(1+0.22)^$C$13:$G$13)+$G$12*(1+0.07)/(0.22-0.07)/(1+0.22)^5-'Forecast Assumptions'!C22+'Forecast Assumptions'!C23)/'Forecast Assumptions'!C21 -> 346.50314 | G34: =(SUMPRODUCT($C$12:$G$12,1/(1+0.22)^$C$13:$G$13)+$G$12*(1+0.08)/(0.22-0.08)/(1+0.22)^5-'Forecast Assumptions'!C22+'Forecast Assumptions'!C23)/'Forecast Assumptions'!C21 -> 364.59013

Sheet Comparable Companies
B2: Comparable Company Valuation
B4: Company | C4: Share price (₦) | D4: Market cap (₦bn) | E4: Enterprise value (₦bn) | F4: Revenue (₦bn) | G4: EBITDA (₦bn) | H4: Net income (₦bn) | I4: EV / EBITDA | J4: P / E
B5: Dangote Cement | C5: 1066.7 | D5: 18175 | E5: 19125 | F5: 4306.704 | G5: 1981.349 | H5: 970 | I5: =E5/G5 -> 9.6525145 | J5: =D5/H5 -> 18.737113
B6: BUA Cement | C6: 125 | D6: 4230 | E6: 4580 | F6: 1150 | G6: 420 | H6: 190 | I6: =E6/G6 -> 10.904762 | J6: =D6/H6 -> 22.263158
B7: Lafarge Africa | C7: 115 | D7: 1852 | E7: 1952 | F7: 1050 | G7: 360 | H7: 220 | I7: =E7/G7 -> 5.4222222 | J7: =D7/H7 -> 8.4181818
B9: Median | I9: =MEDIAN(I5:I7) -> 9.6525145 | J9: =MEDIAN(J5:J7) -> 18.737113
B11: Cross-check | C11: Value | D11: Method
B12: Dangote implied EV | C12: =I9*G5 -> 19125 | D12: Median EV/EBITDA × Dangote EBITDA
B13: Implied equity value | C13: =C12-'Forecast Assumptions'!C22+'Forecast Assumptions'!C23 -> 18175 | D13: Implied EV - net debt
B14: Implied value per share | C14: =C13/'Forecast Assumptions'!C21 -> 1066.608 | D14: Equity value / shares outstanding
B16: Important note
B17: Peer inputs status | C17: Illustrative placeholders for workbook demonstration. Replace with same-date market values and latest reported LTM financials before using the output.
B18: Selection logic | C18: Nigerian listed cement producers with broadly comparable sector exposure. Differences in geography, scale, leverage and accounting must be considered.

Sheet Dashboard
B2: Dangote Cement | Investment Research Dashboard
B4: Implied Value / Share | E4: Reference Price | G4: Upside / (Downside) | J4: Recommendation
B5: ='DCF Valuation'!C23 -> 402.08086 | E5: ='DCF Valuation'!C24 -> 1066.7 | G5: ='DCF Valuation'!C25 -> -0.62306098 | J5: ='DCF Valuation'!C26 -> SELL
B7: Investment Thesis | H7: Key Risks & Catalysts
B8: Base case: revenue growth and operating leverage support cash-flow generation, while high nominal discount rates and execution risks constrain valuation. The model recommendation is formula-driven: Buy above +15% upside, Sell below -15%, otherwise Hold. Update all yellow assumptions and peer data before presenting the conclusion. | H8: Type | I8: Factor | J8: Impact
H9: Risk | I9: Energy/fuel inflation | J9: Margin compression
H10: Risk | I10: FX and higher yields | J10: Higher costs and WACC
H11: Catalyst | I11: Pricing and volume growth | J11: Revenue upside
H12: Catalyst | I12: Operating leverage | J12: Margin and FCF upside
B13: Year | C13: Revenue | D13: EBITDA | E13: Net income
B14: 2023A | C14: 2400 | D14: 950 | E14: 435
B15: 2024A | C15: 3500 | D15: 1380 | E15: 630 | H15: Year | I15: EBITDA margin | J15: Net margin
B16: 2025A | C16: 4306.704 | D16: 1981.349 | E16: 970 | H16: 2023A | I16: ='Historical Financials'!C28 -> 0.39583333 | J16: ='Historical Financials'!C29 -> 0.18125
H17: 2024A | I17: ='Historical Financials'!D28 -> 0.39428571 | J17: ='Historical Financials'!D29 -> 0.18
H18: 2025A | I18: ='Historical Financials'!E28 -> 0.46006157 | J18: ='Historical Financials'!E29 -> 0.22523025
B39: Analyst Checkout
B40: Question | C40: Status | D40: Evidence / next action
B41: Are historical figures sourced? | C41: Partial | D41: 2025 headline figures cited; replace illustrative placeholders
B42: Are forecasts linked to assumptions? | C42: Yes | D42: Formula-driven forecast sheet
B43: Is valuation triangulated? | C43: Yes | D43: DCF plus peer multiples
B44: Are material risks identified? | C44: Yes | D44: Macro, operating, leverage and ESG
B45: Can another analyst audit the model? | C45: Yes | D45: Separated inputs, formulas and source notes

Sheet Sources
B2: Sources, Data Status & Model Limitations
B4: Source | C4: URL | D4: Data used | E4: As of / period | F4: Status
B5: Dangote Cement Investor Relations | C5: https://cement.dangote.com/investor-relations/ | D5: 2025 revenue ₦4,306.704bn; EBITDA ₦1,981.349bn; capacity 55.0MTA; share price ₦1,066.70 | E5: Share price 16 Oct 2026; FY2025 results | F5: Official
B6: Dangote Cement 2025 Annual Report page | C6: https://cement.dangote.com/annual-report-2025/ | D6: Primary reference for annual report update | E6: FY2025 | F6: Official
B7: NGX 2025 audited financial statements | C7: https://doclib.ngxgroup.com/Financial_NewsDocs/DANGOTE_CEMENT_PLC_-_2025_AUDITED_FINANCIAL_STATEMENTS.pdf | D7: Primary filing for detailed statement replacement | E7: FY2025 | F7: Official filing
B8: Model author assumptions | C8: Internal workbook cells | D8: Historical placeholders, forecasts, WACC and peer data | E8: Illustrative | F8: Must be refreshed
B10: Model limitation
B11: This workbook is for a portfolio demonstration, not investment advice.
B12: Illustrative inputs are deliberately visible in blue/yellow and identified by source/status notes.
B13: Valuation is highly sensitive to WACC, terminal growth, margins and capital expenditure.
